omnicreader.cpython-310-aarch64-linux-gnu.so
omnicreader-0.0.2.dist-info/METADATA
omnicreader-0.0.2.dist-info/top_level.txt
omnicreader-0.0.2.dist-info/WHEEL
omnicreader-0.0.2.dist-info/RECORD
