Metadata-Version: 2.1
Name: omnicreader
Version: 0.0.2
Summary: OMNIC file reader
Author: Marko Toplak
Author-email: marko.toplak@gmail.com
Keywords: omnic
